ratiopath/openslide.py
ratiopath/augmentations/__init__.py
ratiopath/augmentations/estimate_stain_vectors.py
ratiopath/augmentations/stain_augmentor.py
ratiopath/masks/__init__.py
ratiopath/masks/tissue_mask.py
ratiopath/masks/vips_filters/__init__.py
ratiopath/masks/vips_filters/color_filters.py
ratiopath/masks/vips_filters/typed.py
ratiopath/masks/vips_filters/vips_filter.py
ratiopath/masks/vips_filters/vips_morphology.py
ratiopath/masks/vips_filters/vips_multi_otsu.py
ratiopath/parsers/__init__.py
ratiopath/parsers/asap_parser.py
ratiopath/parsers/geojson_parser.py
ratiopath/ray/__init__.py
ratiopath/ray/read_slides.py
ratiopath/ray/datasource/__init__.py
ratiopath/ray/datasource/slide_metadatasource.py
ratiopath/ray/datasource/vips_tiff_datasink.py
ratiopath/tiling/__init__.py
ratiopath/tiling/annotations.py
ratiopath/tiling/read_slide_tiles.py
ratiopath/tiling/tilers.py
ratiopath/tiling/utils.py
ratiopath/tiling/masks/mask.py
ratiopath/torch/data/openslide_tile_reader.py
ratiopath/torch/data/overlay.py
ratiopath/torch/data/slide.py
ratiopath/utils/__init__.py
ratiopath/utils/closest_level.py
ratiopath-1.0.3.dist-info/licenses/LICENSE
ratiopath-1.0.3.dist-info/METADATA
ratiopath-1.0.3.dist-info/WHEEL
ratiopath-1.0.3.dist-info/top_level.txt
ratiopath-1.0.3.dist-info/RECORD
