Metadata-Version: 2.4
Name: ratiopath
Version: 1.0.3
Summary: A library for efficient processing and analysis of whole-slide pathology images.
Author-email: Matěj Pekár <matejpekar@mail.muni.cz>, Jakub Pekár <jakubpekar@mail.muni.cz>, Adam Kukučka <adamkukucka@mail.muni.cz>
License-Expression: MIT
Project-URL: Homepage, https://github.com/RationAI/ratiopath
Requires-Python: >=3.11
License-File: LICENSE
Requires-Dist: albumentations>=2.0.8
Requires-Dist: imagecodecs>=2025.8.2
Requires-Dist: numpy>=2.2.2
Requires-Dist: ome-types>=0.6.1
Requires-Dist: openslide-python>=1.4.1
Requires-Dist: pandas>=2.2.3
Requires-Dist: pandas-stubs>=2.2.3.250308
Requires-Dist: pillow>=11.1.0
Requires-Dist: pyvips>=2.2.3
Requires-Dist: ray[data]>=2.42.1
Requires-Dist: scikit-image>=0.25.2
Requires-Dist: tifffile>=2024.5.22
Requires-Dist: shapely>=2.0.0
Requires-Dist: torch>=2.6.0
Requires-Dist: zarr>=3.1.1
Requires-Dist: geopandas>=1.1.1
Provides-Extra: docs
Requires-Dist: mkdocs-material>=9.6.18; extra == "docs"
Requires-Dist: mkdocstrings[python]>=0.30.0; extra == "docs"
Provides-Extra: tests
Requires-Dist: openslide-bin>=4.0.0.8; extra == "tests"
Requires-Dist: pytest>=8.4.1; extra == "tests"
Dynamic: license-file
